{
  "project_info": {
    "project_number": "484532011950",
    "project_id": "foodplanet-abdc5",
    "storage_bucket": "foodplanet-abdc5.appspot.com"
  },
  "client": [
    {
      "client_info": {
        "mobilesdk_app_id": "1:484532011950:android:e0123788da1ed7e37f7e3f",
        "android_client_info": {
          "package_name": "com.foodplanet"
        }
      },
      "oauth_client": [
        {
          "client_id": "484532011950-qhdgpbasuaqi8trgkpioqljbgqfh002u.apps.googleusercontent.com",
          "client_type": 3
        }
      ],
      "api_key": [
        {
          "current_key": "AIzaSyBbl8mamYgNBaXFh8GopYridNH01OxjlzU"
        }
      ],
      "services": {
        "appinvite_service": {
          "other_platform_oauth_client": [
            {
              "client_id": "484532011950-qhdgpbasuaqi8trgkpioqljbgqfh002u.apps.googleusercontent.com",
              "client_type": 3
            }
          ]
        }
      }
    }
  ],
  "configuration_version": "1"
}